__init__.py
default.py
is_even_20220929-1.0.1.dist-info/LICENSE
is_even_20220929-1.0.1.dist-info/METADATA
is_even_20220929-1.0.1.dist-info/WHEEL
is_even_20220929-1.0.1.dist-info/top_level.txt
is_even_20220929-1.0.1.dist-info/RECORD
