Metadata-Version: 2.1
Name: is-even-20220929
Version: 1.0.1
Summary: Determine whether a number is even or odd
Author-email: Metin <metin@example.com>
Project-URL: Homepage, https://github.com/
Classifier: Programming Language :: Python :: 3
Classifier: License :: OSI Approved :: MIT License
Classifier: Operating System :: OS Independent
Requires-Python: >=3.7
License-File: LICENSE
